{
  "gameDate": "2026-03-10",
  "difficulty": "medium",
  "results": [
    {
      "category": "general_knowledge",
      "id": "647638d1f05ea6d6f587a156",
      "correctAnswer": "Répondez S'il Vous Plaît",
      "incorrectAnswers": [
        "Rester Sans Vôtre Poisson",
        "Respond Soon Via Phone",
        "Request Some Vacation Plans"
      ],
      "question": {
        "text": "What does the 4-letter abbreviation RSVP stand for?"
      },
      "tags": [
        "abbreviations",
        "initials",
        "society_and_culture",
        "general_knowledge"
      ],
      "type": "text_choice",
      "difficulty": "medium",
      "regions": [],
      "isNiche": false
    },
    {
      "category": "history",
      "id": "622a1c357cc59eab6f94fde3",
      "correctAnswer": "Spain ",
      "incorrectAnswers": [
        "Italy",
        "England",
        "France"
      ],
      "question": {
        "text": "Which Country's Royalty Paid For Christopher Columbus 's First Voyage Across The Atlantic?"
      },
      "tags": [
        "exploration",
        "history"
      ],
      "type": "text_choice",
      "difficulty": "medium",
      "regions": [],
      "isNiche": false
    },
    {
      "category": "society_and_culture",
      "id": "622a1c377cc59eab6f950456",
      "correctAnswer": "Church of Scientology",
      "incorrectAnswers": [
        "The Chuch of Jesus Christ of Latter-day Saints",
        "The Jehovah's Witnesses",
        "The Church of the Flying Spaghetti Monster"
      ],
      "question": {
        "text": "Deriving its name from the Latin word meaning knowledge, which church was founded in 1954 in California?"
      },
      "tags": [
        "society_and_culture"
      ],
      "type": "text_choice",
      "difficulty": "medium",
      "regions": [],
      "isNiche": false
    },
    {
      "category": "sport_and_leisure",
      "id": "64f3a941601ffca0b7615dd7",
      "correctAnswer": "A beanball",
      "incorrectAnswers": [
        "A curveball",
        "A fastball",
        "A slider"
      ],
      "question": {
        "text": "What is the baseball term for when a pitcher intentionally hits a batter with the pitch?"
      },
      "tags": [
        "baseball",
        "sport"
      ],
      "type": "text_choice",
      "difficulty": "medium",
      "regions": [],
      "isNiche": false
    },
    {
      "category": "food_and_drink",
      "id": "639898405c9a75021f31046c",
      "correctAnswer": "Fermentation",
      "incorrectAnswers": [
        "Distillation",
        "Oxidation",
        "Clarification"
      ],
      "question": {
        "text": "What is the process used to convert grape juice into wine called?"
      },
      "tags": [
        "food_and_drink",
        "wine",
        "drink",
        "chemistry"
      ],
      "type": "text_choice",
      "difficulty": "medium",
      "regions": [],
      "isNiche": false
    },
    {
      "category": "society_and_culture",
      "id": "622a1c367cc59eab6f9500ea",
      "correctAnswer": "Apollo",
      "incorrectAnswers": [
        "Orion",
        "Morpheus",
        "Prometheus"
      ],
      "question": {
        "text": "Who was the Greek god of prophecy and archery?"
      },
      "tags": [
        "society_and_culture"
      ],
      "type": "text_choice",
      "difficulty": "medium",
      "regions": [],
      "isNiche": false
    },
    {
      "category": "arts_and_literature",
      "id": "622a1c3a7cc59eab6f951397",
      "correctAnswer": "Alice's Adventures in Wonderland",
      "incorrectAnswers": [
        "Charlotte's Web",
        "The Hobbit",
        "Taras Bulba"
      ],
      "question": {
        "text": "In which book does The Queen of Hearts appear?"
      },
      "tags": [
        "fictitious_characters",
        "literature",
        "childrens_literature",
        "arts_and_literature"
      ],
      "type": "text_choice",
      "difficulty": "medium",
      "regions": [],
      "isNiche": false
    },
    {
      "category": "arts_and_literature",
      "id": "622a1c377cc59eab6f95042c",
      "correctAnswer": "Jacob Marley",
      "incorrectAnswers": [
        "Archie Scorn",
        "Marius Topman",
        "Ronald Leerden"
      ],
      "question": {
        "text": "In The Charles Dickens Novel 'A Chrismas Carol' Who Was Scrooge's Dead Business Partner? "
      },
      "tags": [
        "arts_and_literature"
      ],
      "type": "text_choice",
      "difficulty": "medium",
      "regions": [],
      "isNiche": false
    },
    {
      "category": "history",
      "id": "622a1c3c7cc59eab6f951a0c",
      "correctAnswer": "Henry Kissinger",
      "incorrectAnswers": [
        "John Quincy Adams",
        "Condoleezza Rice",
        "Robert Gates"
      ],
      "question": {
        "text": "Which U.S. Secretary of State won the Nobel Peace Prize in 1973?"
      },
      "tags": [
        "usa",
        "politics",
        "history"
      ],
      "type": "text_choice",
      "difficulty": "medium",
      "regions": [],
      "isNiche": false
    },
    {
      "category": "society_and_culture",
      "id": "622a1c367cc59eab6f950381",
      "correctAnswer": "Pontius Pilate",
      "incorrectAnswers": [
        "Cesar Augustus",
        "King Solomon",
        "Judas"
      ],
      "question": {
        "text": "Who presided over the trial of Jesus?"
      },
      "tags": [
        "christianity",
        "society_and_culture"
      ],
      "type": "text_choice",
      "difficulty": "medium",
      "regions": [],
      "isNiche": false
    },
    {
      "category": "society_and_culture",
      "id": "626288684b176d54800e3d9a",
      "correctAnswer": "BMW",
      "incorrectAnswers": [
        "Harley Davidson",
        "Mercedez-Benz",
        "Porsche"
      ],
      "question": {
        "text": "Which motoring brand is associated with the marketing slogan 'The Ultimate Driving Machine'?"
      },
      "tags": [
        "business",
        "marketing",
        "motoring",
        "society_and_culture"
      ],
      "type": "text_choice",
      "difficulty": "medium",
      "regions": [],
      "isNiche": false
    },
    {
      "category": "society_and_culture",
      "id": "622a1c367cc59eab6f950408",
      "correctAnswer": "Rosa Parks",
      "incorrectAnswers": [
        "Angela Davis",
        "Dorothy Cotton",
        "Fanny Lou Hamer"
      ],
      "question": {
        "text": "Which civil right activist is famous for refusing to give up her seat on a bus to make way for a white person?"
      },
      "tags": [
        "general_knowledge",
        "people",
        "society_and_culture"
      ],
      "type": "text_choice",
      "difficulty": "medium",
      "regions": [],
      "isNiche": false
    },
    {
      "category": "arts_and_literature",
      "id": "622a1c367cc59eab6f950168",
      "correctAnswer": "Piglet",
      "incorrectAnswers": [
        "Roo",
        "Finnie",
        "Paddington"
      ],
      "question": {
        "text": "Who was Winnie the Pooh's neighbour?"
      },
      "tags": [
        "arts_and_literature"
      ],
      "type": "text_choice",
      "difficulty": "medium",
      "regions": [],
      "isNiche": false
    },
    {
      "category": "geography",
      "id": "623b5792fd6c701a92118367",
      "correctAnswer": "Japan",
      "incorrectAnswers": [
        "Vietnam",
        "Russia",
        "France"
      ],
      "question": {
        "text": "In which country would you find the Itsukushima Shinto Shrine?"
      },
      "tags": [
        "tourist_attractions",
        "places",
        "geography"
      ],
      "type": "text_choice",
      "difficulty": "medium",
      "regions": [],
      "isNiche": false
    },
    {
      "category": "science",
      "id": "622a1c397cc59eab6f950fb6",
      "correctAnswer": "Gregor Mendel",
      "incorrectAnswers": [
        "Alexander Graham Bell",
        "Thomas Edison",
        "Charles Darwin"
      ],
      "question": {
        "text": "Who is known as the father of genetics?"
      },
      "tags": [
        "people",
        "science"
      ],
      "type": "text_choice",
      "difficulty": "medium",
      "regions": [],
      "isNiche": false
    },
    {
      "category": "geography",
      "id": "622a1c387cc59eab6f9507fe",
      "correctAnswer": "Africa",
      "incorrectAnswers": [
        "South America",
        "Oceania",
        "Europe"
      ],
      "question": {
        "text": "The country of Togo is on which continent?"
      },
      "tags": [
        "geography"
      ],
      "type": "text_choice",
      "difficulty": "medium",
      "regions": [],
      "isNiche": false
    },
    {
      "category": "music",
      "id": "645aba5e158db1bd1779f1ce",
      "correctAnswer": "The Beatles",
      "incorrectAnswers": [
        "The Rolling Stones",
        "The Beach Boys",
        "The Who"
      ],
      "question": {
        "text": "Which band's '1962-1966' and '1967-1970' albums sold 13 million copies and 14 million copies respectively?"
      },
      "tags": [
        "bands",
        "music",
        "music_albums"
      ],
      "type": "text_choice",
      "difficulty": "medium",
      "regions": [],
      "isNiche": false
    },
    {
      "category": "science",
      "id": "646089e1de964ebc39016c94",
      "correctAnswer": "Charles Goodyear",
      "incorrectAnswers": [
        "Henry Ford",
        "Thomas Edison",
        "Eli Whitney"
      ],
      "question": {
        "text": "In 1839, which American inventor reportedly spilled a mix of rubber and sulfur onto a hot stove and found that it didn't melt?"
      },
      "tags": [
        "inventors",
        "history",
        "chemistry",
        "science"
      ],
      "type": "text_choice",
      "difficulty": "medium",
      "regions": [],
      "isNiche": false
    },
    {
      "category": "film_and_tv",
      "id": "62573fbf3d2f5c16bfb8833b",
      "correctAnswer": "Inglourious Basterds",
      "incorrectAnswers": [
        "Hotel Rwanda",
        "Snatch",
        "Cool Hand Luke"
      ],
      "question": {
        "text": "Name the movie that matches the following plot summary: 'During World War II, a group of Jewish U.S. soldiers plan to assassinate Nazi leaders.'"
      },
      "tags": [
        "film",
        "film_and_tv"
      ],
      "type": "text_choice",
      "difficulty": "medium",
      "regions": [],
      "isNiche": false
    },
    {
      "category": "food_and_drink",
      "id": "64dd35bb9cef2bd3a34a8d60",
      "correctAnswer": "Melons",
      "incorrectAnswers": [
        "Oranges",
        "Apples",
        "Bananas"
      ],
      "question": {
        "text": "What is the common name for the fruits named casaba, crenshaw, and honeydew?"
      },
      "tags": [
        "fruit",
        "food",
        "food_and_drink"
      ],
      "type": "text_choice",
      "difficulty": "medium",
      "regions": [],
      "isNiche": false
    },
    {
      "category": "arts_and_literature",
      "id": "622a1c3a7cc59eab6f95135c",
      "correctAnswer": "Minimalism",
      "incorrectAnswers": [
        "Simplicism",
        "Aesthetics",
        "Surrealism"
      ],
      "question": {
        "text": "Which art movement emphasized pure, reduced forms and strict, systematic composition?"
      },
      "tags": [
        "art",
        "arts_and_literature"
      ],
      "type": "text_choice",
      "difficulty": "medium",
      "regions": [],
      "isNiche": false
    },
    {
      "category": "music",
      "id": "622a1c377cc59eab6f95043f",
      "correctAnswer": "Ringo Starr",
      "incorrectAnswers": [
        "Ricky Martin",
        "Kanye West",
        "Bob Marley"
      ],
      "question": {
        "text": "How in the world of music is Richard Starkey more commonly known?"
      },
      "tags": [
        "pseudonyms",
        "people",
        "music"
      ],
      "type": "text_choice",
      "difficulty": "medium",
      "regions": [],
      "isNiche": false
    },
    {
      "category": "geography",
      "id": "64e6536e0b79e5bedd549515",
      "correctAnswer": "Hudson Bay",
      "incorrectAnswers": [
        "Erie Bay",
        "Superior Bay",
        "Georgian Bay"
      ],
      "question": {
        "text": "James Bay, located in Ontario and Quebec, is the southern arm of which larger bay?"
      },
      "tags": [
        "bodies_of_water",
        "canada",
        "bays",
        "geography"
      ],
      "type": "text_choice",
      "difficulty": "medium",
      "regions": [],
      "isNiche": false
    },
    {
      "category": "history",
      "id": "622a1c3b7cc59eab6f95177b",
      "correctAnswer": "Bangladesh",
      "incorrectAnswers": [
        "Sri Lanka",
        "Bhutan",
        "Pakistan"
      ],
      "question": {
        "text": "Which new country was formed in 1971 at the end of a conflict between Pakistan and India?"
      },
      "tags": [
        "history",
        "1970's",
        "wars"
      ],
      "type": "text_choice",
      "difficulty": "medium",
      "regions": [],
      "isNiche": false
    },
    {
      "category": "film_and_tv",
      "id": "622a1c377cc59eab6f950733",
      "correctAnswer": "Ralph Fiennes",
      "incorrectAnswers": [
        "Brian Cox",
        "Mark Wahlberg",
        "Leonardo DiCaprio"
      ],
      "question": {
        "text": "Which actor has starred in both Harry Potter and Skyfall?"
      },
      "tags": [
        "acting",
        "film",
        "film_and_tv"
      ],
      "type": "text_choice",
      "difficulty": "medium",
      "regions": [],
      "isNiche": false
    },
    {
      "category": "science",
      "id": "622a1c3f7cc59eab6f952356",
      "correctAnswer": "Sulfur",
      "incorrectAnswers": [
        "Hydrogen",
        "Chlorine",
        "Gold"
      ],
      "question": {
        "text": "What chemical element is brimstone synonymous with?"
      },
      "tags": [
        "science"
      ],
      "type": "text_choice",
      "difficulty": "medium",
      "regions": [],
      "isNiche": false
    },
    {
      "category": "science",
      "id": "622a1c3e7cc59eab6f952322",
      "correctAnswer": "Real & Imaginary",
      "incorrectAnswers": [
        "True & False",
        "Big & Small",
        "Logical & Intuitive"
      ],
      "question": {
        "text": "What are the 2 parts of complex numbers known as?"
      },
      "tags": [
        "mathematics",
        "science"
      ],
      "type": "text_choice",
      "difficulty": "medium",
      "regions": [],
      "isNiche": false
    },
    {
      "category": "history",
      "id": "64746ac15a4c31088dd9cfde",
      "correctAnswer": "Bay of Pigs",
      "incorrectAnswers": [
        "Bay of Cows",
        "Bay of Dogs",
        "Bay of Sharks"
      ],
      "question": {
        "text": "What is the name given to the USA's failed 1961 invasion of Cuba?"
      },
      "tags": [
        "usa",
        "cold_war",
        "history",
        "1960's",
        "wars",
        "cuba"
      ],
      "type": "text_choice",
      "difficulty": "medium",
      "regions": [],
      "isNiche": false
    },
    {
      "category": "general_knowledge",
      "id": "622a1c357cc59eab6f94fc90",
      "correctAnswer": "Cacophony",
      "incorrectAnswers": [
        "Cabotage",
        "Gardyloo",
        "Halfpace"
      ],
      "question": {
        "text": "Which word is defined as 'a harsh, discordant mixture of sounds'?"
      },
      "tags": [
        "words",
        "general_knowledge"
      ],
      "type": "text_choice",
      "difficulty": "medium",
      "regions": [],
      "isNiche": false
    },
    {
      "category": "history",
      "id": "63989c1e5c9a75021f310482",
      "correctAnswer": "France",
      "incorrectAnswers": [
        "England",
        "Spain",
        "Germany"
      ],
      "question": {
        "text": "Which country was the main power in Europe during the 17th century?"
      },
      "tags": [
        "history",
        "1600s",
        "europe"
      ],
      "type": "text_choice",
      "difficulty": "medium",
      "regions": [],
      "isNiche": false
    }
  ]
}
