{
  "gameDate": "2026-07-16",
  "difficulty": "hard",
  "results": [
    {
      "category": "science",
      "id": "622a1c3e7cc59eab6f9522fd",
      "correctAnswer": "Lungs",
      "incorrectAnswers": [
        "Heart",
        "Skin",
        "Eyes"
      ],
      "question": {
        "text": "Emphysema Affects Which Part Of The Body?"
      },
      "tags": [
        "science"
      ],
      "type": "text_choice",
      "difficulty": "hard",
      "regions": [],
      "isNiche": false
    },
    {
      "category": "geography",
      "id": "6233877f0161109f922aac2a",
      "correctAnswer": "China",
      "incorrectAnswers": [
        "Russia",
        "Brazil",
        "Canada"
      ],
      "question": {
        "text": "Which country has the longest land border?"
      },
      "tags": [
        "geography"
      ],
      "type": "text_choice",
      "difficulty": "hard",
      "regions": [],
      "isNiche": false
    },
    {
      "category": "general_knowledge",
      "id": "647f9db33a4302a719271615",
      "correctAnswer": "Bracchium",
      "incorrectAnswers": [
        "Caput",
        "Pedis",
        "Oculus"
      ],
      "question": {
        "text": "What is the Latin term for \"the arm\"?"
      },
      "tags": [
        "anatomy",
        "latin",
        "language",
        "words"
      ],
      "type": "text_choice",
      "difficulty": "hard",
      "regions": [],
      "isNiche": false
    },
    {
      "category": "history",
      "id": "622a1c377cc59eab6f95042f",
      "correctAnswer": "Concorde",
      "incorrectAnswers": [
        "The Channel Tunnel",
        "Eurostar",
        "An animal cloning plant"
      ],
      "question": {
        "text": "In 1962, for what did Britain and France sign an agreement to build together?"
      },
      "tags": [
        "history"
      ],
      "type": "text_choice",
      "difficulty": "hard",
      "regions": [],
      "isNiche": false
    },
    {
      "category": "history",
      "id": "64861cecf773f09dc0193b47",
      "correctAnswer": "The Tower of London",
      "incorrectAnswers": [
        "Windsor Castle",
        "Buckingham Palace",
        "St. James's Palace"
      ],
      "question": {
        "text": "What is the name of the royal fortress on the Thames River that includes Traitors' Gate?"
      },
      "tags": [
        "tourist_attractions",
        "castles",
        "history",
        "london"
      ],
      "type": "text_choice",
      "difficulty": "hard",
      "regions": [],
      "isNiche": false
    },
    {
      "category": "film_and_tv",
      "id": "625fd6c7dc0dd3b72da64d0a",
      "correctAnswer": "2009",
      "incorrectAnswers": [
        "2003",
        "2005",
        "2007"
      ],
      "question": {
        "text": "In which year was Inglourious Basterds first released in the cinema?"
      },
      "tags": [
        "film",
        "film_and_tv"
      ],
      "type": "text_choice",
      "difficulty": "hard",
      "regions": [],
      "isNiche": false
    },
    {
      "category": "film_and_tv",
      "id": "622a1c367cc59eab6f9501db",
      "correctAnswer": "Francis Ford Coppola",
      "incorrectAnswers": [
        "Steven Spielberg",
        "Woody Allen",
        "Martin Scorsese"
      ],
      "question": {
        "text": "Which director directed Apocalypse Now?"
      },
      "tags": [
        "film_and_tv"
      ],
      "type": "text_choice",
      "difficulty": "hard",
      "regions": [],
      "isNiche": false
    },
    {
      "category": "arts_and_literature",
      "id": "622a1c347cc59eab6f94f978",
      "correctAnswer": "Lonesome Dove",
      "incorrectAnswers": [
        "In Our Time",
        "The Moviegoer",
        "The Swimmer"
      ],
      "question": {
        "text": "Which book contains the character 'Augustus McCrae'?"
      },
      "tags": [
        "literature",
        "fictitious_characters",
        "arts_and_literature"
      ],
      "type": "text_choice",
      "difficulty": "hard",
      "regions": [],
      "isNiche": false
    },
    {
      "category": "history",
      "id": "6488deed50a27f7378a91de8",
      "correctAnswer": "A shield",
      "incorrectAnswers": [
        "A sword",
        "A helmet",
        "A spear"
      ],
      "question": {
        "text": "Used by the Roman military, what was a Scutum?"
      },
      "tags": [
        "military",
        "arms",
        "weapons",
        "the_romans"
      ],
      "type": "text_choice",
      "difficulty": "hard",
      "regions": [],
      "isNiche": false
    },
    {
      "category": "history",
      "id": "62611fdb4b176d54800e3d75",
      "correctAnswer": "1992",
      "incorrectAnswers": [
        "1987",
        "1997",
        "2002"
      ],
      "question": {
        "text": "When was the first SMS message sent?"
      },
      "tags": [
        "events",
        "firsts",
        "inventions",
        "technology",
        "history"
      ],
      "type": "text_choice",
      "difficulty": "hard",
      "regions": [],
      "isNiche": false
    },
    {
      "category": "music",
      "id": "622a1c387cc59eab6f950bda",
      "correctAnswer": "Guns N' Roses",
      "incorrectAnswers": [
        "MercyMe",
        "The Pussycat Dolls",
        "Three 6 Mafia"
      ],
      "question": {
        "text": "Which American hard rock band released the studio album 'Use Your Illusion I'?"
      },
      "tags": [
        "music"
      ],
      "type": "text_choice",
      "difficulty": "hard",
      "regions": [],
      "isNiche": false
    },
    {
      "category": "film_and_tv",
      "id": "622a1c377cc59eab6f9505b9",
      "correctAnswer": "Jacqueline Bisset",
      "incorrectAnswers": [
        "Sophia Loren",
        "Mila Kunis",
        "Hilary Duff"
      ],
      "question": {
        "text": "Which actress has starred in films including Murder on the Orient Express and Casino Royale?"
      },
      "tags": [
        "film_and_tv"
      ],
      "type": "text_choice",
      "difficulty": "hard",
      "regions": [],
      "isNiche": false
    },
    {
      "category": "film_and_tv",
      "id": "622a1c367cc59eab6f95039e",
      "correctAnswer": "Jingle All The Way",
      "incorrectAnswers": [
        "The Santa Clause",
        "Miracle on 34th Street",
        "Bad Santa"
      ],
      "question": {
        "text": "Which Popular Christmas Movie Featured A Must Have Toy Called 'Turbo Man''"
      },
      "tags": [
        "film_and_tv"
      ],
      "type": "text_choice",
      "difficulty": "hard",
      "regions": [],
      "isNiche": false
    },
    {
      "category": "science",
      "id": "622a1c377cc59eab6f9504fb",
      "correctAnswer": "mollusks",
      "incorrectAnswers": [
        "the Earth",
        "dialects",
        "religion"
      ],
      "question": {
        "text": "What is Malacology the study of?"
      },
      "tags": [
        "science"
      ],
      "type": "text_choice",
      "difficulty": "hard",
      "regions": [],
      "isNiche": false
    },
    {
      "category": "music",
      "id": "622a1c397cc59eab6f950c35",
      "correctAnswer": "Depeche Mode",
      "incorrectAnswers": [
        "Level 42",
        "Dead or Alive",
        "Radiohead"
      ],
      "question": {
        "text": "Which English band released the album 'Black Celebration'?"
      },
      "tags": [
        "music"
      ],
      "type": "text_choice",
      "difficulty": "hard",
      "regions": [],
      "isNiche": false
    },
    {
      "category": "arts_and_literature",
      "id": "622a1c347cc59eab6f94f985",
      "correctAnswer": "The Tin Drum",
      "incorrectAnswers": [
        "Gone With the Wind",
        "In Our Time",
        "Portnoy's Complaint"
      ],
      "question": {
        "text": "Which book contains the character 'Oskar Matzerath'?"
      },
      "tags": [
        "literature",
        "fictitious_characters",
        "arts_and_literature"
      ],
      "type": "text_choice",
      "difficulty": "hard",
      "regions": [],
      "isNiche": false
    },
    {
      "category": "science",
      "id": "622a1c3e7cc59eab6f95229f",
      "correctAnswer": "3",
      "incorrectAnswers": [
        "1",
        "0",
        "2"
      ],
      "question": {
        "text": "How many hearts does an octopus have?"
      },
      "tags": [
        "animals",
        "science",
        "numbers",
        "biology"
      ],
      "type": "text_choice",
      "difficulty": "hard",
      "regions": [],
      "isNiche": false
    },
    {
      "category": "general_knowledge",
      "id": "6473075ccf09068746f63770",
      "correctAnswer": "Aqueducts",
      "incorrectAnswers": [
        "Canals",
        "Pipelines",
        "Trenches"
      ],
      "question": {
        "text": "What type of structures are used to conduct a water stream across a valley?"
      },
      "tags": [
        "architecture",
        "civil_engineering",
        "engineering"
      ],
      "type": "text_choice",
      "difficulty": "hard",
      "regions": [],
      "isNiche": false
    },
    {
      "category": "science",
      "id": "622a1c3a7cc59eab6f9510c6",
      "correctAnswer": "Two",
      "incorrectAnswers": [
        "Five",
        "Four",
        "Three"
      ],
      "question": {
        "text": "How many beams of light are used to record a holograph?"
      },
      "tags": [
        "science"
      ],
      "type": "text_choice",
      "difficulty": "hard",
      "regions": [],
      "isNiche": false
    },
    {
      "category": "geography",
      "id": "6233863262eaad73716a8cbc",
      "correctAnswer": "Paris ",
      "incorrectAnswers": [
        "Madrid",
        "Rome",
        "Brussels"
      ],
      "question": {
        "text": "Where is Le Figaro published?"
      },
      "tags": [
        "geography"
      ],
      "type": "text_choice",
      "difficulty": "hard",
      "regions": [],
      "isNiche": false
    },
    {
      "category": "film_and_tv",
      "id": "622a1c377cc59eab6f950717",
      "correctAnswer": "Helen Mirren",
      "incorrectAnswers": [
        "Kathy Bates",
        "Kirsten Dunst",
        "Sandra Bæ Hovedr"
      ],
      "question": {
        "text": "Which actress has played roles in films including The Queen and National Treasure: Book of Secrets?"
      },
      "tags": [
        "acting",
        "film",
        "film_and_tv"
      ],
      "type": "text_choice",
      "difficulty": "hard",
      "regions": [],
      "isNiche": false
    },
    {
      "category": "music",
      "id": "625064cce12f6dec240bdfce",
      "correctAnswer": "Jane Child",
      "incorrectAnswers": [
        "Lou Bega",
        "Big Country",
        "Jeannie C. Riley"
      ],
      "question": {
        "text": "Who had a hit in 1990 with Don't Wanna Fall in Love?"
      },
      "tags": [
        "songs",
        "one_hit_wonders",
        "music"
      ],
      "type": "text_choice",
      "difficulty": "hard",
      "regions": [],
      "isNiche": false
    },
    {
      "category": "music",
      "id": "622a1c357cc59eab6f94fdc4",
      "correctAnswer": "Pat Benatar",
      "incorrectAnswers": [
        "Blondie",
        "Patti Smith",
        "Patti Cake$"
      ],
      "question": {
        "text": "Patricia Andrzejewski Is The Real Name Of Which Singer"
      },
      "tags": [
        "pseudonyms",
        "names",
        "music"
      ],
      "type": "text_choice",
      "difficulty": "hard",
      "regions": [],
      "isNiche": false
    },
    {
      "category": "film_and_tv",
      "id": "622a1c347cc59eab6f94fbdd",
      "correctAnswer": "\"It’s the sense of touch. In any real city, you walk, you know? You brush past people, people bump into you. In L.A., nobody touches you. We’re always behind this metal and glass. I think we miss that touch so much, that we crash into each other, just so we can feel something.\"",
      "incorrectAnswers": [
        "\"May the Force be with you.\"",
        "\"Here's looking at you, kid.\"",
        "\"What is this? A center for ants? How can we be expected to teach children to learn how to read…if they can’t even fit inside the building?\""
      ],
      "question": {
        "text": "Which of these quotes is from the film 'Crash'?"
      },
      "tags": [
        "quotes",
        "film",
        "film_and_tv"
      ],
      "type": "text_choice",
      "difficulty": "hard",
      "regions": [],
      "isNiche": false
    },
    {
      "category": "film_and_tv",
      "id": "622a1c347cc59eab6f94fb3b",
      "correctAnswer": "American Beauty",
      "incorrectAnswers": [
        "The Cider House Rules",
        "The Green Mile",
        "The Insider"
      ],
      "question": {
        "text": "Which film won the Academy Award for Best Picture in 1999?"
      },
      "tags": [
        "academy_awards",
        "film",
        "film_and_tv"
      ],
      "type": "text_choice",
      "difficulty": "hard",
      "regions": [],
      "isNiche": false
    },
    {
      "category": "film_and_tv",
      "id": "622a1c367cc59eab6f950217",
      "correctAnswer": "Ridley Scott",
      "incorrectAnswers": [
        "Steven Spielberg",
        "Woody Allen",
        "Martin Scorsese"
      ],
      "question": {
        "text": "Which director directed Blade Runner?"
      },
      "tags": [
        "film_and_tv"
      ],
      "type": "text_choice",
      "difficulty": "hard",
      "regions": [],
      "isNiche": false
    },
    {
      "category": "film_and_tv",
      "id": "625740c69da29df7b05f73f7",
      "correctAnswer": "A rogue wins the heart of a rich widow and assumes her dead husband's aristocratic position.",
      "incorrectAnswers": [
        "A naive youth leader is appointed to fill a vacancy in the U.S. Senate.",
        "After a girl is uprooted from her life, her emotions conflict on how best to navigate a new life.",
        "A family heads to a hotel for the winter where a presence influences the father into violence."
      ],
      "question": {
        "text": "What is the plot of the movie Barry Lyndon?"
      },
      "tags": [
        "film",
        "film_and_tv"
      ],
      "type": "text_choice",
      "difficulty": "hard",
      "regions": [],
      "isNiche": false
    },
    {
      "category": "science",
      "id": "6244372e746187c5e7be9339",
      "correctAnswer": "Baking Soda",
      "incorrectAnswers": [
        "Bleach",
        "Table Salt",
        "Dolomite"
      ],
      "question": {
        "text": "What is the common name for sodium bicarbonate?"
      },
      "tags": [
        "chemistry",
        "general_knowledge",
        "names",
        "science"
      ],
      "type": "text_choice",
      "difficulty": "hard",
      "regions": [],
      "isNiche": false
    },
    {
      "category": "sport_and_leisure",
      "id": "622a1c347cc59eab6f94f85f",
      "correctAnswer": "Motor Racing",
      "incorrectAnswers": [
        "Cycling",
        "Tennis",
        "Cricket"
      ],
      "question": {
        "text": "With which sport is Sterling Moss associated?"
      },
      "tags": [
        "people",
        "sport"
      ],
      "type": "text_choice",
      "difficulty": "hard",
      "regions": [],
      "isNiche": false
    },
    {
      "category": "society_and_culture",
      "id": "622a1c357cc59eab6f94fcc0",
      "correctAnswer": "Kra–Dai",
      "incorrectAnswers": [
        "Sino-Tibetan",
        "Austroasiatic",
        "Afroasiatic"
      ],
      "question": {
        "text": "The language 'Thai' belongs to which language family?"
      },
      "tags": [
        "language",
        "society_and_culture"
      ],
      "type": "text_choice",
      "difficulty": "hard",
      "regions": [],
      "isNiche": false
    }
  ]
}
